{
  "summary": {
    "suiteName": "User Registration Suite",
    "tags": {
      "serviceName": "digitalLibrary",
      "suiteType": "@regression"
    },
    "totalTestCases": 2,
    "totalDataSets": 3,
    "passed": 3,
    "failed": 0,
    "totalAssertionsPassed": 10,
    "totalAssertionsFailed": 0,
    "executionTimeMs": 1436
  },
  "results": [
    {
      "testCase": "Register New User -Valid data",
      "dataSet": "Create a new User- valid",
      "status": "PASS",
      "assertionsPassed": 4,
      "assertionsFailed": 0,
      "responseTimeMs": 880
    },
    {
      "testCase": "Register New User -Valid data",
      "dataSet": "Create new User - empty body",
      "status": "PASS",
      "assertionsPassed": 2,
      "assertionsFailed": 0,
      "responseTimeMs": 313
    },
    {
      "testCase": "Get User By Email ",
      "dataSet": "Get User By Email - valid",
      "status": "PASS",
      "assertionsPassed": 4,
      "assertionsFailed": 0,
      "responseTimeMs": 241
    }
  ]
}